setup.py
ybc_youtuyun/__init__.py
ybc_youtuyun/auth.py
ybc_youtuyun/conf.py
ybc_youtuyun/youtu.py
ybc_youtuyun.egg-info/PKG-INFO
ybc_youtuyun.egg-info/SOURCES.txt
ybc_youtuyun.egg-info/dependency_links.txt
ybc_youtuyun.egg-info/requires.txt
ybc_youtuyun.egg-info/top_level.txt