Metadata-Version: 1.0
Name: ybc-youtuyun
Version: 1.0.5
Summary: Youtuyun AI Demo
Home-page: UNKNOWN
Author: KingHS
Author-email: 382771946@qq.com
License: MIT License
Keywords: youtuyun ai
Platform: any
